LICENSE
MANIFEST.in
README.md
setup.cfg
setup.py
version.txt
argo/__init__.py
argo/configuration.py
argo/models/__init__.py
argo/models/cronv1alpha1_create_cron_workflow_request.py
argo/models/cronv1alpha1_lint_cron_workflow_request.py
argo/models/cronv1alpha1_update_cron_workflow_request.py
argo/models/google_protobuf_any.py
argo/models/grpc_gateway_runtime_stream_error.py
argo/models/v1alpha1_archive_strategy.py
argo/models/v1alpha1_arguments.py
argo/models/v1alpha1_artifact.py
argo/models/v1alpha1_artifact_location.py
argo/models/v1alpha1_artifact_repository_ref.py
argo/models/v1alpha1_artifactory_artifact.py
argo/models/v1alpha1_artifactory_auth.py
argo/models/v1alpha1_backoff.py
argo/models/v1alpha1_continue_on.py
argo/models/v1alpha1_counter.py
argo/models/v1alpha1_cron_workflow.py
argo/models/v1alpha1_cron_workflow_list.py
argo/models/v1alpha1_cron_workflow_spec.py
argo/models/v1alpha1_cron_workflow_status.py
argo/models/v1alpha1_dag_task.py
argo/models/v1alpha1_dag_template.py
argo/models/v1alpha1_executor_config.py
argo/models/v1alpha1_gauge.py
argo/models/v1alpha1_gcs_artifact.py
argo/models/v1alpha1_gcs_bucket.py
argo/models/v1alpha1_git_artifact.py
argo/models/v1alpha1_hdfs_artifact.py
argo/models/v1alpha1_hdfs_config.py
argo/models/v1alpha1_hdfs_krb_config.py
argo/models/v1alpha1_histogram.py
argo/models/v1alpha1_http_artifact.py
argo/models/v1alpha1_info_response.py
argo/models/v1alpha1_inputs.py
argo/models/v1alpha1_item.py
argo/models/v1alpha1_item_value.py
argo/models/v1alpha1_link.py
argo/models/v1alpha1_log_entry.py
argo/models/v1alpha1_metadata.py
argo/models/v1alpha1_metric_label.py
argo/models/v1alpha1_metrics.py
argo/models/v1alpha1_node_status.py
argo/models/v1alpha1_oss_artifact.py
argo/models/v1alpha1_oss_bucket.py
argo/models/v1alpha1_outputs.py
argo/models/v1alpha1_parameter.py
argo/models/v1alpha1_pod_gc.py
argo/models/v1alpha1_prometheus.py
argo/models/v1alpha1_raw_artifact.py
argo/models/v1alpha1_resource_template.py
argo_models.egg-info/PKG-INFO
argo_models.egg-info/SOURCES.txt
argo_models.egg-info/dependency_links.txt
argo_models.egg-info/not-zip-safe
argo_models.egg-info/requires.txt
argo_models.egg-info/top_level.txt