Metadata-Version: 2.1
Name: argo-models
Version: 2.7.5
Summary: Generated openapi models for Argo objects.
Home-page: https://github.com/e2fyi/argo-models
Author: william teo
Author-email: eterna2@hotmail.com
License: UNKNOWN
Download-URL: https://github.com/e2fyi/argo-models/archive/v2.7.5.tar.gz
Keywords: argo openapi swagger kubeflow
Platform: UNKNOWN
Classifier: Development Status :: 3 - Alpha
Classifier: Intended Audience :: Developers
Classifier: Natural Language :: English
Classifier: Programming Language :: Python :: 2.7
Classifier: Programming Language :: Python :: 3
Classifier: Programming Language :: Python :: 3.5
Classifier: Programming Language :: Python :: 3.6
Classifier: Programming Language :: Python :: 3.7
Classifier: License :: OSI Approved :: Apache Software License
Requires-Python: >=2.7,!=3.0.*,!=3.1.*,!=3.2.*,!=3.3.*,!=3.4.*
